LICENSE
MANIFEST.in
README.md
package.json
setup.py
dash_tabulator/DashTabulator.py
dash_tabulator/__init__.py
dash_tabulator/_imports_.py
dash_tabulator/dash_tabulator.min.js
dash_tabulator/dash_tabulator.min.js.map
dash_tabulator/metadata.json
dash_tabulator/package-info.json
dash_tabulator.egg-info/PKG-INFO
dash_tabulator.egg-info/SOURCES.txt
dash_tabulator.egg-info/dependency_links.txt
dash_tabulator.egg-info/top_level.txt