Metadata-Version: 2.1
Name: dash-tabulator
Version: 0.1.1
Summary: Dash Plotly component providing Tabulator tables
Home-page: https://github.com/preftech/dash-tabulator
Author: patrick oleary <pjaol+dash@pjaol.com>
License: MIT
Platform: UNKNOWN
Classifier: Framework :: Dash
